gwalk/__init__.py
gwalk/gapply.py
gwalk/gcp.py
gwalk/gl.py
gwalk/gwalk.py
pygwalk-0.2.7.dist-info/licenses/LICENSE
pygwalk-0.2.7.dist-info/METADATA
pygwalk-0.2.7.dist-info/WHEEL
pygwalk-0.2.7.dist-info/entry_points.txt
pygwalk-0.2.7.dist-info/top_level.txt
pygwalk-0.2.7.dist-info/RECORD
