Metadata-Version: 2.4
Name: pygwalk
Version: 0.2.7
Summary: gwalk 是一系列用于管理 Git 仓库的命令行小工具，帮助开发者对大批量的 Git 仓库进行日常维护。
Author-email: Zero Kwok <zero.kwok@foxmail.com>
License: MIT License
Project-URL: Homepage, https://github.com/ZeroKwok/gwalk
Project-URL: Issues, https://github.com/ZeroKwok/gwalk/issues
Keywords: git,tools
Classifier: Intended Audience :: Developers
Classifier: Topic :: Software Development :: Build Tools
Classifier: Programming Language :: Python
Classifier: Programming Language :: Python :: 3 :: Only
Classifier: Programming Language :: Python :: 3
Classifier: Programming Language :: Python :: 3.7
Classifier: Programming Language :: Python :: 3.8
Classifier: Programming Language :: Python :: 3.9
Classifier: Programming Language :: Python :: 3.10
Classifier: Programming Language :: Python :: 3.11
Requires-Python: >=3.7
License-File: LICENSE
Requires-Dist: GitPython
Requires-Dist: termcolor
Requires-Dist: natsort
Dynamic: license-file
